Metadata-Version: 2.1
Name: WALEED
Version: 0.post1
Summary: For a test
Author: WALEED
License-File: LICENCE.txt
